pythermiagenesis/__init__.py
pythermiagenesis/const.py
pythermiagenesis-0.1.8.dist-info/licenses/LICENSE
pythermiagenesis-0.1.8.dist-info/METADATA
pythermiagenesis-0.1.8.dist-info/WHEEL
pythermiagenesis-0.1.8.dist-info/top_level.txt
pythermiagenesis-0.1.8.dist-info/RECORD
